authentication/__init__.py
authentication/apps.py
authentication/urls.py
authentication/util.py
authentication/views.py
authentication/static/authentication/css/layout.css
authentication/static/authentication/css/layout.css.map
authentication/static/authentication/js/account.js
authentication/static/authentication/js/layout.js
authentication/static/authentication/js/login.js
authentication/static/authentication/js/recover.js
authentication/static/authentication/js/register.js
authentication/templates/authentication/account.html
authentication/templates/authentication/header.html
authentication/templates/authentication/layout.html
authentication/templates/authentication/login.html
authentication/templates/authentication/handlebars/account.html
authentication/templates/authentication/handlebars/recover.html
authentication/templates/authentication/handlebars/register.html
authentication/templates/authentication/modals/account.html
authentication/templates/authentication/modals/recover.html
authentication/templates/authentication/modals/register.html
django_user_login-0.3.4.dist-info/LICENSE
django_user_login-0.3.4.dist-info/METADATA
django_user_login-0.3.4.dist-info/WHEEL
django_user_login-0.3.4.dist-info/top_level.txt
django_user_login-0.3.4.dist-info/RECORD
