Metadata-Version: 2.1
Name: django-user-login
Version: 0.3.4
Summary: A django user authentication and login application.
Home-page: https://github.com/parisrvs/django-user-login
Author: Parijat Srivastava
Author-email: parisrvs@hotmail.com
Project-URL: Bug Tracker, https://github.com/parisrvs/django-user-login
Requires-Python: >=3.8
License-File: LICENSE
Requires-Dist: Django (>=4.0)
